CahyPublic/TimeHandle.py
CahyPublic/__init__.py
TimeHandle-0.0.1.dist-info/LICENSE
TimeHandle-0.0.1.dist-info/METADATA
TimeHandle-0.0.1.dist-info/WHEEL
TimeHandle-0.0.1.dist-info/top_level.txt
TimeHandle-0.0.1.dist-info/RECORD
