Metadata-Version: 2.1
Name: TimeHandle
Version: 0.0.1
Summary: cahy Test
Home-page: UNKNOWN
Author: cahy-jjw
Author-email: jjwjiawang@163.com
License: UNKNOWN
Platform: UNKNOWN
Classifier: Programming Language :: Python :: 3
